{
      "kidswear":[
  {
    "id": 1,
    "name": "Pink Pochampally Frock",
    "material": "Cotton Silk",
    "type": "Frock",
    "gender": "Girls",
    "price": 1200,
    "discount": 10,
    "finalPrice": 1080,
    "stock": 15,
    "rating": 4.5,
    "reviews": 25,
    "image": "https://i.pinimg.com/736x/9e/7a/3b/9e7a3b59f0a2c8df16cb4223a2ed0571.jpg"
  },
  {
    "id": 2,
    "name": "Blue Pochampally Half Saree ",
    "material": "Silk Cotton",
    "type": "Half Saree",
    "gender": "Girls",
    "price": 1300,
    "discount": 5,
    "finalPrice": 1235,
    "stock": 12,
    "rating": 4.6,
    "reviews": 18,
    "image": "https://i.pinimg.com/736x/d5/68/e5/d568e569bd4182477bd81a9a3e1aa928.jpg"
  },
  {
    "id": 3,
    "name": "Yellow Pochampally Frock",
    "material": "Silk Cotton",
    "type": "Frock",
    "gender": "Girls",
    "price": 1500,
    "discount": 10,
    "finalPrice": 1350,
    "stock": 10,
    "rating": 4.7,
    "reviews": 20,
    "image": "https://i.pinimg.com/736x/ae/12/fb/ae12fb937f155e844157a00d4a1e9b15.jpg"
  },
  {
    "id": 4,
    "name": "Green Pochampally Frock",
    "material": "Cotton",
    "type": "Frock",
    "gender": "Girls",
    "price": 1400,
    "discount": 5,
    "finalPrice": 1330,
    "stock": 18,
    "rating": 4.5,
    "reviews": 22,
    "image": "https://i.pinimg.com/736x/86/2f/1c/862f1cf283ead710cd134a7252160840.jpg"
  },
  {
    "id": 5,
    "name": "White Pochampally Frock",
    "material": "Cotton Silk",
    "type": "Frock",
    "gender": "Girls",
    "price": 600,
    "discount": 10,
    "finalPrice": 540,
    "stock": 14,
    "rating": 4.6,
    "reviews": 18,
    "image": "https://i.pinimg.com/originals/74/24/2e/74242e3ef3409b878d342cab23839b9e.jpg"},
  {
    "id": 6,
    "name": "Orange Pochampally Girls Langavani",
    "material": "Silk Cotton",
    "type": "Langavani",
    "gender": "Girls",
    "price": 1600,
    "discount": 10,
    "finalPrice": 1440,
    "stock": 9,
    "rating": 4.8,
    "reviews": 19,
    "image": "https://i.pinimg.com/originals/2a/63/81/2a638132b77c901662a5c3e4141621d2.jpg"
  },
  {
    "id": 7,
    "name": "Pochampally Frock",
    "material": "Cotton",
    "type": "Frock",
    "gender": "Girls",
    "price": 1500,
    "discount": 0,
    "finalPrice": 1500,
    "stock": 16,
    "rating": 4.5,
    "reviews": 17,
    "image": "https://i.pinimg.com/originals/6c/4d/ba/6c4dbaf4ee868b593cc737f80213f4b6.jpg"
  },
  {
    "id": 8,
    "name": "Purple Pochampally Frock",
    "material": "Cotton Silk",
    "type": "Dress",
    "gender": "Girls",
    "price": 1350,
    "discount": 5,
    "finalPrice": 1282,
    "stock": 13,
    "rating": 4.7,
    "reviews": 21,
    "image": "https://5.imimg.com/data5/SELLER/Default/2022/11/LX/ZG/KR/48616650/3-1000x1000.jpg"
  },
  {
    "id": 9,
    "name": "Blue Pochampally Frock",
    "material": "Silk Cotton",
    "type": "Frock",
    "gender": "Girls",
    "price": 1700,
    "discount": 10,
    "finalPrice": 1530,
    "stock": 11,
    "rating": 4.6,
    "reviews": 16,
    "image": "https://i.pinimg.com/originals/7a/fd/c8/7afdc8ca591ef24e096f4c2d3bf5c6b0.jpg"
  },
  {
    "id": 10,
    "name": "Multicolor Pochampally Girls Frock",
    "material": "Cotton Silk Blend",
    "type": "Frock",
    "gender": "Girls",
    "price": 1300,
    "discount": 0,
    "finalPrice": 1300,
    "stock": 17,
    "rating": 4.5,
    "reviews": 18,
    "image": "https://i.pinimg.com/originals/7b/c5/e5/7bc5e5a0d56649afafad9a2e68c795be.jpg"
  },
  {
    "id": 11,
    "name": "Blue Frock",
    "material": "Cotton",
    "type": "Frock",
    "gender": "Girls",
    "price": 450,
    "discount": 5,
    "finalPrice": 1377,
    "stock": 12,
    "rating": 4.4,
    "reviews": 14,
    "image": "https://i.pinimg.com/originals/09/9f/1b/099f1bf9759d8c538bcb85882f4ea611.jpg"
  },
  {
    "id": 12,
    "name": "Green Pochampally Frock",
    "material": "Cotton Silk",
    "type": "Frock",
    "gender": "Girls",
    "price": 1250,
    "discount": 5,
    "finalPrice": 1187,
    "stock": 14,
    "rating": 4.5,
    "reviews": 19,
    "image": "https://i.pinimg.com/originals/a8/f7/88/a8f788a357b79d7e8e9f5a7c49060ae9.jpg"
  },
  {
    "id": 13,
    "name": "Black Pochampally ",
    "material": "Cotton Silk",
    "type": "Frock",
    "gender": "Girls",
    "price": 1650,
    "discount": 10,
    "finalPrice": 1485,
    "stock": 10,
    "rating": 4.6,
    "reviews": 15,
    "image": "https://i.ytimg.com/vi/OQymPK6iwqc/maxres2.jpg?sqp=-oaymwEoCIAKENAF8quKqQMcGADwAQH4Ac4FgAKACooCDAgAEAEYZSBhKFcwDw==&rs=AOn4CLDeh5H0r0WaUIApxjtDweBM22N60Q"
  },
  {
    "id": 14,
    "name": "Coral Pochampally Girls Langavani",
    "material": "Silk Cotton",
    "type": "Langavani",
    "gender": "Girls",
    "price": 1550,
    "discount": 10,
    "finalPrice": 1395,
    "stock": 11,
    "rating": 4.7,
    "reviews": 17,
    "image": "https://i.pinimg.com/originals/7b/f3/bc/7bf3bc3bf9138a1e08f2425d579724d3.jpg"
  },
  {
    "id": 15,
    "name": "Grey Pochampally",
    "material": "Cotton",
    "type": "Frock",
    "gender": "Girls",
    "price": 1500,
    "discount": 0,
    "finalPrice": 1500,
    "stock": 13,
    "rating": 4.5,
    "reviews": 16,
    "image": "https://i.pinimg.com/236x/c5/3c/a2/c53ca270dca366b7d4dae32e0655f612.jpg"
  },
  {
    "id": 16,
    "name": "Magenta Pochampally Girls Dress",
    "material": "Cotton Silk",
    "type": "Dress",
    "gender": "Girls",
    "price": 1400,
    "discount": 5,
    "finalPrice": 1330,
    "stock": 12,
    "rating": 4.6,
    "reviews": 18,
    "image": "https://i.pinimg.com/originals/72/a2/79/72a2797f249833b18cf0e39ab98851e8.jpg"
  },
  {
    "id": 17,
    "name": "Brown Pochampally ",
    "material": "Cotton Silk",
    "type": "Kurta",
    "gender": "Boys",
    "price": 1600,
    "discount": 10,
    "finalPrice": 1440,
    "stock": 11,
    "rating": 4.6,
    "reviews": 14,
    "image": "https://5.imimg.com/data5/ANDROID/Default/2023/10/356762738/VW/ST/RD/2429868/product-jpeg-500x500.jpg"
  },
  {
    "id": 18,
    "name": " Blue Pochampally Half Saree",
    "material": "Cotton Silk Blend",
    "type": "Half Saree",
    "gender": "Girls",
    "price": 1300,
    "discount": 0,
    "finalPrice": 1300,
    "stock": 16,
    "rating": 4.5,
    "reviews": 15,
    "image": "https://1.bp.blogspot.com/-otim0E03OHA/WGB_EbghvlI/AAAAAAAAKB4/bVOMwMAVfpwgwbV3D1A-3U0KetgRiikWgCLcB/s640/sky-blue-pochampally-lehenga.jpg"
  },
  {
    "id": 19,
    "name": "Pochampally Frock ",
    "material": "Cotton",
    "type": "Frock",
    "gender": "Girls",
    "price": 1450,
    "discount": 5,
    "finalPrice": 1377,
    "stock": 12,
    "rating": 4.4,
    "reviews": 13,
    "image": "https://i.ytimg.com/vi/blSJw27rsTo/hq2.jpg?sqp=-oaymwEoCOADEOgC8quKqQMcGADwAQH4Ac4FgAKACooCDAgAEAEYfyA4KEswDw==&rs=AOn4CLDEV5_Z4hI7Ue0JBLI-MV68lv1qXg"
  },
  {
    "id": 20,
    "name": " Pochampally Girls Langavani",
    "material": "Silk Cotton",
    "type": "Langavani",
    "gender": "Girls",
    "price": 1500,
    "discount": 10,
    "finalPrice": 1350,
    "stock": 10,
    "rating": 4.7,
    "reviews": 16,
    "image": "https://i.pinimg.com/originals/8d/c6/72/8dc672a86284a336dbe9f03176ef333e.jpg"
  }
]
}